skema/__init__.py
skema/__main__.py
skema/constants.py
skema/from_jsonschema.py
skema/make_schema.py
skema/make_tree.py
skema/parser.py
skema/preprocess.py
skema/resolve_refs.py
skema/split_references.py
skema/support.py
skema/to_graphql.py
skema/to_jsonschema.py
skema/tokenize.py
skema/tree.py
skema/fake_data/__init__.py
skema/fake_data/hypo_schema.py
skema/fake_data/regex.py
skema/generate/__init__.py
skema/infer/__init__.py
skema-0.0.42.data/scripts/skema-gen
skema-0.0.42.data/scripts/skema-generate-graphql
skema-0.0.42.data/scripts/skema-generate-jsonschema
skema-0.0.42.data/scripts/skema-generate-python
skema-0.0.42.data/scripts/skema-generate-typescript
skema-0.0.42.data/scripts/skema.generate
skema-0.0.42.data/scripts/skema.infer
skema-0.0.42.dist-info/METADATA
skema-0.0.42.dist-info/WHEEL
skema-0.0.42.dist-info/top_level.txt
skema-0.0.42.dist-info/RECORD
