Metadata-Version: 2.1
Name: skema
Version: 0.0.42
Summary: Schema language that compiles to json schema
Home-page: https://github.com/remorses/schema
Author: Tommaso De Rossi
Author-email: daer.tommy@gmail.com
License: Apache Software License 2.0
Keywords: schema,jsonschema,alternative,readable
Platform: UNKNOWN
Classifier: Intended Audience :: Information Technology
Classifier: License :: OSI Approved :: Apache Software License
Classifier: Programming Language :: Python :: 3
Classifier: Programming Language :: Python :: 3.6
Classifier: Programming Language :: Python :: 3.7
Requires-Dist: fastjsonschema
Requires-Dist: jsonschema
Requires-Dist: bson
Requires-Dist: genson
Requires-Dist: hypothesis
Requires-Dist: graphql-core (==3.0.0a2)
Requires-Dist: funcy
